{
  "cards": [
    {
      "id": "custom-xyp-JP279",
      "name": "Pikachu",
      "alt_name": "ГЈВғВ”ГЈВӮВ«ГЈВғВҒГЈВғВҘГЈВӮВҰ",
      "supertype": "PokГғВ©mon",
      "subtypes": [
        "Basic"
      ],
      "hp": 60,
      "types": [
        "Lightning"
      ],
      "evolves_from": "Pichu",
      "rarity": "Promo",
      "artist": "Naoki Saito",
      "art_style": [
        "Chibi"
      ],
      "set_id": "xyp",
      "set_name": "20th Anniversary Festa",
      "set_series": "XY",
      "number": "XY279",
      "regulation_mark": "",
      "image_small": "https://archives.bulbagarden.net/media/upload/thumb/8/88/PikachuXYPromo279.jpg/360px-PikachuXYPromo279.jpg",
      "image_large": "https://www.serebii.net/card/xypromo/279.jpg",
      "source": "Japan Exclusive",
      "owned": false,
      "notes": "Pikachu is a yellow mouse-like PokГғВ©mon with a lightning bolt shaped mark on its cheeks. It is a short, chubby, and has short, pointed, brown ears and large copper-brown eyes. It has a rounded, pointed snout with a small black nose and two small, pointed teeth visible in its upper jaw.",
      "main_character": [
        "Pikachu"
      ],
      "background_pokemon": [
        "Pikachu"
      ],
      "background_humans": null,
      "primary_color": "Yellow",
      "secondary_color": "Brown",
      "shape": "Round",
      "video_game": "X/Y",
      "video_appearance": false,
      "thumbnail_used": false,
      "video_url": "",
      "video_title": "",
      "unique_id": "xyp-JP279",
      "evolution_line": [
        "pichu",
        "pikachu",
        "raichu"
      ],
      "emotion": "Happy",
      "pose": "Jumping",
      "camera_angle": "Front",
      "items": "20th Anniversary Trophy",
      "actions": "Jumping",
      "additional_characters": [
        "Bulbasaur",
        "Charmander",
        "Squirtle"
      ],
      "perspective": "",
      "weather_environment": "Indoors",
      "storytelling": "Celebration",
      "background_details": [
        "Trophy",
        "Throne",
        "Confetti"
      ],
      "card_locations": "Nagoya",
      "pkmn_region": "Johto"
    },
    {
      "id": "custom-xyp-JP289",
      "name": "Lass' Special",
      "alt_name": "ГЈВғВҹГЈВғВӢГЈВӮВ№ГЈВӮВ«ГЈВғВјГЈВғВҲГЈВҒВ®ГЈВҒВҠГЈВҒВҷГЈВҒВҷГЈВӮВҒ",
      "supertype": "Trainer",
      "subtypes": [
        "Supporter"
      ],
      "hp": null,
      "types": [],
      "evolves_from": null,
      "rarity": "Promo",
      "artist": "Yusuke Ohmura",
      "art_style": [
        "Cartoon"
      ],
      "set_id": "xyp",
      "set_name": "20th Anniversary Festa",
      "set_series": "XY",
      "number": "XY289",
      "regulation_mark": "",
      "image_small": "https://archives.bulbagarden.net/media/upload/thumb/5/58/LassRecommendationMAudinoEXMegaBattleDeck24.jpg/360px-LassRecommendationMAudinoEXMegaBattleDeck24.jpg",
      "image_large": "https://www.serebii.net/card/xypromo/289.jpg",
      "source": "Japan Exclusive",
      "owned": false,
      "notes": "",
      "main_character": "Lass",
      "background_pokemon": [
        "Roselia"
      ],
      "background_humans": null,
      "primary_color": "Black",
      "secondary_color": "Red",
      "shape": "Human",
      "video_game": "X/Y",
      "video_appearance": false,
      "thumbnail_used": false,
      "video_url": "",
      "video_title": "",
      "unique_id": "xyp-JP289",
      "evolution_line": null,
      "emotion": "Happy",
      "pose": "Arms Stretched Out",
      "camera_angle": "Front",
      "items": "Poke Ball",
      "actions": "Standing",
      "additional_characters": null,
      "perspective": "",
      "weather_environment": "Sunny",
      "storytelling": "",
      "background_details": [
        "Statue",
        "Cafe",
        "Water Fountain"
      ],
      "card_locations": "Santalune City",
      "pkmn_region": ""
    },
    {
      "id": "custom-vm-set3-28",
      "name": "Machoke",
      "alt_name": "ГЈВӮВҙГЈВғВјГЈВғВӘГЈВӮВӯГЈВғВј",
      "supertype": "Pokemon",
      "subtypes": [
        "Stage 1"
      ],
      "hp": 60,
      "types": [
        "Fighting"
      ],
      "evolves_from": "Machop",
      "rarity": "Promo",
      "artist": "Tomokazu Komiya",
      "art_style": [
        "Paper"
      ],
      "set_id": "vm-s3",
      "set_name": "Vending Machine Set 3",
      "set_series": "VM3",
      "number": "VM3-28",
      "regulation_mark": "",
      "image_small": "https://tcgplayer-cdn.tcgplayer.com/product/617537_in_1000x1000.jpg",
      "image_large": "https://tcgplayer-cdn.tcgplayer.com/product/617537_in_1000x1000.jpg",
      "source": "Japan Exclusive",
      "owned": false,
      "notes": "",
      "main_character": "Machoke",
      "background_pokemon": [
        "Ditto",
        "Sandshrew",
        "Chansey",
        "Doduo"
      ],
      "background_humans": null,
      "primary_color": "Purple",
      "secondary_color": "Red",
      "shape": "Human",
      "video_game": null,
      "video_appearance": false,
      "thumbnail_used": false,
      "video_url": "",
      "video_title": "",
      "unique_id": "vm-set3-28",
      "evolution_line": null,
      "emotion": "Happy",
      "pose": "Arms Overhead",
      "camera_angle": "Front",
      "items": null,
      "actions": "Holding Pokemon",
      "additional_characters": [
        "Friends"
      ],
      "perspective": "",
      "weather_environment": "Sunny",
      "storytelling": "",
      "background_details": [
        "River",
        "Trees"
      ],
      "card_locations": "",
      "pkmn_region": ""
    },
    {
      "id": "custom-bjp-094",
      "name": "Gengar",
      "alt_name": "",
      "supertype": "PokГ©mon",
      "subtypes": [
        "Stage 2"
      ],
      "hp": 80,
      "types": [
        "Psychic"
      ],
      "evolves_from": "Haunter",
      "rarity": "JP Promo",
      "special_rarity": "",
      "artist": "Hironabu Yoshida",
      "set_id": "bjp",
      "set_name": "Base Japanese Promos",
      "set_series": "Base",
      "number": "094",
      "regulation_mark": "",
      "image_small": "https://images.scrydex.com/pokemon/miscp_ja-76/large",
      "image_large": "https://images.scrydex.com/pokemon/miscp_ja-76/large",
      "source": "Japan Exclusive",
      "_table": "tcg",
      "owned": false,
      "notes": "",
      "art_style": [],
      "main_character": [],
      "background_pokemon": [],
      "background_humans": null,
      "shape": "",
      "video_game": [],
      "video_game_location": [],
      "shorts_appearance": false,
      "region_appearance": false,
      "thumbnail_used": false,
      "video_title": [],
      "video_type": [],
      "top_10_themes": [],
      "wtpc_episode": [],
      "video_region": [],
      "video_location": [],
      "unique_id": "bjp-094",
      "evolution_line": "gastly вҶ’  haunter вҶ’  gengar",
      "emotion": [
        "Evil"
      ],
      "pose": [
        "Cocky"
      ],
      "camera_angle": "",
      "items": "",
      "actions": [],
      "additional_characters": [],
      "perspective": "",
      "weather": "",
      "environment": "",
      "background_details": [
        "purgatory"
      ],
      "card_locations": "The Void",
      "pkmn_region": "",
      "card_subcategory": [],
      "held_item": "",
      "pokeball": "",
      "evolution_items": [],
      "berries": [],
      "holiday_theme": [],
      "multi_card": [],
      "trainer_card_type": "",
      "trainer_card_subgroup": [],
      "pocket_exclusive": false,
      "stamp": "",
      "card_border": "Beige",
      "energy_type": "",
      "rival_group": "",
      "additional_character_theme": [],
      "image_override": "",
      "video_url": ""
    }
  ]
}
